smd/__init__.py
smd/__main__.py
smd/downloader.py
smd/utils.py
smd/locale/es/LC_MESSAGES/smd.mo
smd-1.6.1.dist-info/METADATA
smd-1.6.1.dist-info/RECORD
smd-1.6.1.dist-info/WHEEL
smd-1.6.1.dist-info/entry_points.txt
smd-1.6.1.dist-info/top_level.txt
