Metadata-Version: 2.1
Name: smd
Version: 1.6.1
Summary: Simple Manga Downloader, a tool to search and download manga for offline reading
Home-page: https://adbenitez.github.io/smd
Author: adbenitez
Author-email: asieldbenitez@gmail.com
License: GPL3+
Project-URL: Documentation, http://smd.readthedocs.io
Project-URL: Tracker, https://github.com/adbenitez/smd/issues
Project-URL: Donate, http://liberapay.com/adbenitez
Project-URL: Source, https://github.com/adbenitez/smd
Project-URL: Say Thanks!, http://mastodon.social/@adbenitez
Keywords: download manga downloader web scraping crawler spider internet desktop app offline reading
Platform: UNKNOWN
Classifier: Development Status :: 5 - Production/Stable
Classifier: Intended Audience :: End Users/Desktop
Classifier: Environment :: Console
Classifier: Environment :: Web Environment
Classifier: Programming Language :: Python :: 3
Classifier: License :: OSI Approved :: GNU General Public License v3 or later (GPLv3+)
Classifier: Natural Language :: English
Classifier: Operating System :: OS Independent
Classifier: Topic :: Games/Entertainment
Classifier: Topic :: Internet
Classifier: Topic :: Internet :: WWW/HTTP
Classifier: Topic :: Utilities
Requires-Python: >=3
Requires-Dist: beautifulsoup4
